easymail.py
easymail-0.3.0.dist-info/DESCRIPTION.rst
easymail-0.3.0.dist-info/METADATA
easymail-0.3.0.dist-info/RECORD
easymail-0.3.0.dist-info/WHEEL
easymail-0.3.0.dist-info/metadata.json
easymail-0.3.0.dist-info/top_level.txt
