Metadata-Version: 2.0
Name: easymail
Version: 0.3.0
Summary: abstraction layer on top of the email package to make sending    emails a little bit easier
Home-page: https://github.com/mfussenegger/easymail
Author: Mathias Fussenegger
Author-email: pip@zignar.net
License: MIT
Platform: any
Classifier: Development Status :: 4 - Beta
Classifier: Programming Language :: Python
Classifier: Programming Language :: Python :: 3.5
Classifier: Intended Audience :: Developers
Classifier: Intended Audience :: System Administrators
Classifier: License :: OSI Approved :: MIT License
Classifier: Topic :: Internet :: WWW/HTTP
Classifier: Topic :: Software Development
Classifier: Topic :: System :: Networking
